finazon_grpc_python/__init__.py
finazon_grpc_python/api_usage_pb2.py
finazon_grpc_python/api_usage_pb2.pyi
finazon_grpc_python/api_usage_pb2_grpc.py
finazon_grpc_python/api_usage_service.py
finazon_grpc_python/benzinga_pb2.py
finazon_grpc_python/benzinga_pb2.pyi
finazon_grpc_python/benzinga_pb2_grpc.py
finazon_grpc_python/benzinga_service.py
finazon_grpc_python/binance_pb2.py
finazon_grpc_python/binance_pb2.pyi
finazon_grpc_python/binance_pb2_grpc.py
finazon_grpc_python/binance_service.py
finazon_grpc_python/common/__init__.py
finazon_grpc_python/common/client.py
finazon_grpc_python/common/errors.py
finazon_grpc_python/common/settings.py
finazon_grpc_python/common/utils.py
finazon_grpc_python/crypto_pb2.py
finazon_grpc_python/crypto_pb2.pyi
finazon_grpc_python/crypto_pb2_grpc.py
finazon_grpc_python/crypto_service.py
finazon_grpc_python/datasets_pb2.py
finazon_grpc_python/datasets_pb2.pyi
finazon_grpc_python/datasets_pb2_grpc.py
finazon_grpc_python/datasets_service.py
finazon_grpc_python/examples/__init__.py
finazon_grpc_python/examples/indicator_atr.py
finazon_grpc_python/examples/indicator_ma.py
finazon_grpc_python/examples/indicator_ma_pandas.py
finazon_grpc_python/examples/tickers.py
finazon_grpc_python/examples/time_series.py
finazon_grpc_python/examples/time_series_pandas.py
finazon_grpc_python/exchange_pb2.py
finazon_grpc_python/exchange_pb2.pyi
finazon_grpc_python/exchange_pb2_grpc.py
finazon_grpc_python/exchange_service.py
finazon_grpc_python/forex_pb2.py
finazon_grpc_python/forex_pb2.pyi
finazon_grpc_python/forex_pb2_grpc.py
finazon_grpc_python/forex_service.py
finazon_grpc_python/publishers_pb2.py
finazon_grpc_python/publishers_pb2.pyi
finazon_grpc_python/publishers_pb2_grpc.py
finazon_grpc_python/publishers_service.py
finazon_grpc_python/sec_pb2.py
finazon_grpc_python/sec_pb2.pyi
finazon_grpc_python/sec_pb2_grpc.py
finazon_grpc_python/sec_service.py
finazon_grpc_python/sip_pb2.py
finazon_grpc_python/sip_pb2.pyi
finazon_grpc_python/sip_pb2_grpc.py
finazon_grpc_python-1.2.1.dist-info/LICENSE.txt
finazon_grpc_python-1.2.1.dist-info/METADATA
finazon_grpc_python-1.2.1.dist-info/WHEEL
finazon_grpc_python-1.2.1.dist-info/RECORD
