Metadata-Version: 2.1
Name: finazon-grpc-python
Version: 1.2.1
Summary: Finazon gRPC client library for Python
Home-page: https://github.com/finazon-io/finazon-grpc-python
License: MIT
Author: Finazon
Author-email: team@finazon.io
Requires-Python: >=3.9,<4.0
Classifier: License :: OSI Approved :: MIT License
Classifier: Programming Language :: Python :: 3
Classifier: Programming Language :: Python :: 3.9
Classifier: Programming Language :: Python :: 3.10
Classifier: Programming Language :: Python :: 3.11
Classifier: Programming Language :: Python :: 3.12
Provides-Extra: pandas
Requires-Dist: grpcio (>=1.62.1,<2.0.0)
Requires-Dist: grpcio-tools (>=1.62.1,<2.0.0)
Requires-Dist: mypy-protobuf (>=3.5.0,<4.0.0)
Requires-Dist: pandas (>=2.2.1,<3.0.0) ; extra == "pandas"
Project-URL: Repository, https://github.com/finazon-io/finazon-grpc-python
